miceshare/__init__.py
miceshare/classifying.py
miceshare/configs.py
miceshare/hson.py
miceshare/init_all_stocks.py
miceshare/kaipan.py
miceshare/kdata.py
miceshare/log.py
miceshare/miceshare_test.py
miceshare/plot_util.py
miceshare/sink_sqlite.py
miceshare/sixquant.py
miceshare/stock_utils.py
miceshare/db/__init__.py
miceshare/db/data_access.py
miceshare/db/mysql_access.py
miceshare/db/sqlite_util.py
miceshare/util/__init__.py
miceshare/util/stock_utils.py
miceshare/util/vars.py
miceshare-0.0.17.dist-info/DESCRIPTION.rst
miceshare-0.0.17.dist-info/METADATA
miceshare-0.0.17.dist-info/RECORD
miceshare-0.0.17.dist-info/WHEEL
miceshare-0.0.17.dist-info/metadata.json
miceshare-0.0.17.dist-info/top_level.txt
