Metadata-Version: 2.0
Name: miceshare
Version: 0.0.17
Summary: china stock finance market
Home-page: https://gitlab.com/SmartChinaStock/stock_decision_center
Author: cjj
Author-email: cjjvictory@gmail.com
License: MIT
Keywords: stock data machine learn
Platform: UNKNOWN
Classifier: Development Status :: 3 - Alpha
Classifier: Intended Audience :: Developers
Classifier: Topic :: Software Development :: Build Tools
Classifier: License :: OSI Approved :: MIT License
Classifier: Programming Language :: Python :: 3
Classifier: Programming Language :: Python :: 3.3
Classifier: Programming Language :: Python :: 3.4
Classifier: Programming Language :: Python :: 3.5
